architrice/__init__.py
architrice/__main__.py
architrice/caching.py
architrice/database.py
architrice/deckreprs.py
architrice/main.py
architrice/utils.py
architrice/modes/__init__.py
architrice/modes/clear_cards.py
architrice/modes/cli.py
architrice/modes/common.py
architrice/modes/common_json.py
architrice/modes/delete.py
architrice/modes/edit_json.py
architrice/modes/export_json.py
architrice/modes/import_json.py
architrice/modes/latest.py
architrice/modes/mode.py
architrice/modes/output.py
architrice/modes/profile.py
architrice/modes/relnk.py
architrice/modes/sync.py
architrice/modes/version.py
architrice/sources/__init__.py
architrice/sources/archidekt.py
architrice/sources/deckstats.py
architrice/sources/moxfield.py
architrice/sources/source.py
architrice/sources/tappedout.py
architrice/targets/__init__.py
architrice/targets/card_info.py
architrice/targets/cockatrice.py
architrice/targets/generic.py
architrice/targets/mtgo.py
architrice/targets/target.py
architrice/targets/xmage.py
architrice-0.0.6.dist-info/LICENSE
architrice-0.0.6.dist-info/METADATA
architrice-0.0.6.dist-info/WHEEL
architrice-0.0.6.dist-info/top_level.txt
architrice-0.0.6.dist-info/RECORD
