Metadata-Version: 2.1
Name: architrice
Version: 0.0.6
Summary: Utility to sync MtG decklists with online sources.
Home-page: https://github.com/OwenFeik/architrice.git
Author: Owen Feik
Author-email: owen.h.feik@gmail.com
License: UNKNOWN
Download-URL: https://github.com/OwenFeik/architrice/archive/refs/tags/0.0.5.tar.gz
Platform: UNKNOWN
Classifier: Programming Language :: Python :: 3.7
Classifier: License :: OSI Approved :: GNU General Public License v3 (GPLv3)
Classifier: Development Status :: 3 - Alpha
Classifier: Operating System :: POSIX
Classifier: Operating System :: Microsoft :: Windows
Requires-Python: >=3.7
Requires-Dist: requests
Requires-Dist: bs4
